{
    "information": {
        "filename": "08_174534_221206_07.jpg",
        "resolution": [
            1920,
            1080
        ]
    },
    "Scene_meta": {
        "zone": "Anyang, Smart square",
        "edge_case": [
            "곡선 구간 차선 유지"
        ],
        "scene_number": "08_174534_221206"
    },
    "Environment_meta": {
        "weather": "맑음",
        "date": "2022-12-06",
        "time": "17:45:34",
        "car_type": "G80",
        "traffic_Type": 2,
        "speed_type": 0,
        "road_type": "자동차전용도로"
    },
    "annotations": [
        {
            "polygon": [
                0,
                0,
                1920,
                0,
                1920,
                1080,
                0,
                1080
            ],
            "class": "background"
        },
        {
            "polygon": [
                0,
                833,
                307,
                801,
                434,
                789,
                477,
                792,
                499,
                799,
                544,
                800,
                600,
                803,
                802,
                812,
                826,
                816,
                902,
                821,
                1076,
                834,
                1124,
                833,
                1201,
                840,
                1316,
                848,
                1490,
                853,
                1702,
                892,
                1920,
                910,
                1920,
                1080,
                0,
                1080
            ],
            "class": "freespace"
        },
        {
            "polygon": [
                438,
                809,
                461,
                814,
                471,
                820,
                474,
                826,
                472,
                832,
                467,
                835,
                446,
                834,
                449,
                822,
                442,
                814
            ],
            "class": "safetyZone"
        },
        {
            "polygon": [
                1448,
                861,
                1459,
                861,
                1484,
                863,
                1484,
                867,
                1453,
                863
            ],
            "class": "whiteLane"
        },
        {
            "polygon": [
                790,
                850,
                825,
                864,
                838,
                864,
                785,
                843
            ],
            "class": "whiteLane"
        },
        {
            "polygon": [
                428,
                807,
                443,
                808,
                457,
                811,
                467,
                815,
                474,
                820,
                478,
                825,
                477,
                830,
                470,
                836,
                450,
                847,
                394,
                864,
                323,
                885,
                295,
                893,
                287,
                891,
                338,
                877,
                411,
                855,
                439,
                847,
                457,
                839,
                469,
                831,
                471,
                827,
                468,
                821,
                459,
                816,
                448,
                812,
                443,
                811,
                453,
                817,
                456,
                822,
                455,
                827,
                449,
                835,
                437,
                844,
                417,
                851,
                365,
                865,
                287,
                887,
                186,
                913,
                0,
                954,
                0,
                948,
                112,
                923,
                283,
                884,
                368,
                861,
                428,
                844,
                442,
                833,
                444,
                831,
                436,
                831,
                440,
                826,
                441,
                821,
                437,
                816,
                425,
                813
            ],
            "class": "whiteLane"
        },
        {
            "polygon": [
                544,
                923,
                588,
                883,
                601,
                886,
                562,
                925
            ],
            "class": "whiteLane"
        },
        {
            "polygon": [
                165,
                922,
                226,
                906,
                242,
                906,
                183,
                921
            ],
            "class": "whiteLane"
        },
        {
            "polygon": [
                0,
                959,
                79,
                941,
                95,
                943,
                0,
                966
            ],
            "class": "whiteLane"
        },
        {
            "polygon": [
                0,
                935,
                6,
                932,
                0,
                929
            ],
            "class": "roadMark"
        },
        {
            "polygon": [
                0,
                923,
                44,
                926,
                52,
                925,
                52,
                923,
                0,
                920
            ],
            "class": "roadMark"
        },
        {
            "polygon": [
                0,
                905,
                7,
                903,
                11,
                905,
                2,
                908,
                3,
                909,
                19,
                908,
                30,
                908,
                27,
                911,
                22,
                913,
                34,
                912,
                31,
                918,
                19,
                918,
                18,
                913,
                0,
                913
            ],
            "class": "roadMark"
        },
        {
            "polygon": [
                442,
                783,
                442,
                771,
                448,
                770,
                469,
                770,
                470,
                779,
                476,
                780,
                482,
                786,
                475,
                795,
                471,
                799,
                453,
                799,
                450,
                793
            ],
            "class": "truck"
        },
        {
            "polygon": [
                240,
                765,
                270,
                766,
                278,
                770,
                291,
                782,
                299,
                772,
                305,
                768,
                346,
                768,
                353,
                769,
                364,
                777,
                383,
                777,
                398,
                778,
                402,
                780,
                415,
                780,
                421,
                782,
                428,
                794,
                431,
                800,
                431,
                823,
                430,
                828,
                419,
                828,
                418,
                823,
                412,
                823,
                412,
                833,
                408,
                836,
                398,
                836,
                398,
                832,
                382,
                832,
                382,
                839,
                379,
                843,
                361,
                847,
                356,
                847,
                356,
                842,
                314,
                843,
                314,
                855,
                311,
                861,
                305,
                863,
                299,
                864,
                295,
                863,
                294,
                854,
                283,
                855,
                282,
                861,
                280,
                866,
                275,
                869,
                267,
                870,
                256,
                869,
                255,
                868,
                254,
                862,
                227,
                867,
                214,
                864,
                188,
                800
            ],
            "class": "vehicle"
        },
        {
            "polygon": [
                264,
                688,
                273,
                696,
                274,
                703,
                272,
                709,
                267,
                714,
                260,
                717,
                250,
                717,
                241,
                710,
                236,
                701,
                236,
                684
            ],
            "class": "trafficSign"
        },
        {
            "polygon": [
                0,
                542,
                19,
                548,
                36,
                560,
                53,
                589,
                90,
                589,
                164,
                618,
                165,
                622,
                177,
                622,
                197,
                621,
                212,
                625,
                233,
                636,
                241,
                656,
                244,
                671,
                261,
                678,
                269,
                684,
                275,
                692,
                276,
                703,
                273,
                718,
                262,
                723,
                258,
                723,
                259,
                693,
                245,
                691,
                243,
                691,
                248,
                749,
                250,
                815,
                251,
                858,
                244,
                865,
                232,
                868,
                229,
                881,
                223,
                891,
                213,
                895,
                205,
                896,
                192,
                896,
                178,
                892,
                174,
                883,
                172,
                878,
                120,
                885,
                114,
                903,
                106,
                914,
                94,
                919,
                74,
                919,
                64,
                911,
                58,
                894,
                31,
                893,
                20,
                889,
                0,
                885
            ],
            "class": "schoolBus"
        },
        {
            "polygon": [
                311,
                740,
                319,
                740,
                323,
                744,
                323,
                752,
                319,
                757,
                312,
                757,
                308,
                753,
                308,
                745
            ],
            "class": "trafficSign"
        },
        {
            "polygon": [
                323,
                717,
                329,
                717,
                333,
                722,
                333,
                730,
                329,
                734,
                322,
                734,
                319,
                730,
                319,
                722
            ],
            "class": "trafficSign"
        },
        {
            "polygon": [
                352,
                745,
                358,
                745,
                363,
                749,
                363,
                757,
                360,
                761,
                351,
                761,
                347,
                756,
                347,
                749
            ],
            "class": "trafficSign"
        },
        {
            "polygon": [
                377,
                696,
                386,
                696,
                392,
                701,
                392,
                710,
                387,
                715,
                377,
                715,
                372,
                711,
                372,
                700
            ],
            "class": "trafficSign"
        },
        {
            "polygon": [
                428,
                786,
                433,
                780,
                442,
                779,
                450,
                780,
                457,
                785,
                457,
                795,
                455,
                799,
                449,
                799,
                433,
                799,
                427,
                798,
                427,
                788
            ],
            "class": "vehicle"
        },
        {
            "polygon": [
                470,
                787,
                475,
                779,
                481,
                775,
                490,
                774,
                500,
                774,
                508,
                779,
                510,
                787,
                510,
                802,
                509,
                803,
                496,
                803,
                496,
                798,
                482,
                798,
                482,
                803,
                472,
                803,
                469,
                802
            ],
            "class": "vehicle"
        },
        {
            "polygon": [
                537,
                788,
                539,
                779,
                542,
                776,
                548,
                776,
                553,
                775,
                583,
                775,
                592,
                782,
                595,
                786,
                601,
                778,
                606,
                760,
                618,
                745,
                627,
                740,
                630,
                740,
                630,
                742,
                688,
                740,
                742,
                742,
                742,
                739,
                747,
                739,
                757,
                748,
                768,
                771,
                783,
                772,
                789,
                776,
                799,
                778,
                808,
                786,
                813,
                795,
                813,
                806,
                811,
                814,
                806,
                819,
                801,
                819,
                800,
                825,
                796,
                827,
                799,
                843,
                800,
                898,
                801,
                929,
                797,
                936,
                776,
                936,
                770,
                932,
                769,
                913,
                739,
                915,
                711,
                908,
                700,
                913,
                693,
                908,
                668,
                908,
                634,
                918,
                623,
                916,
                612,
                913,
                611,
                927,
                608,
                934,
                600,
                940,
                581,
                940,
                577,
                935,
                575,
                869,
                575,
                829,
                579,
                806,
                562,
                806,
                562,
                812,
                549,
                812,
                548,
                808,
                548,
                801,
                537,
                801
            ],
            "class": "vehicle"
        },
        {
            "polygon": [
                894,
                791,
                907,
                774,
                914,
                767,
                922,
                763,
                928,
                761,
                933,
                761,
                946,
                761,
                1000,
                761,
                1011,
                762,
                1028,
                777,
                1035,
                787,
                1048,
                798,
                1051,
                824,
                1050,
                849,
                1047,
                872,
                1039,
                879,
                1029,
                881,
                1019,
                877,
                1013,
                864,
                939,
                866,
                930,
                867,
                929,
                874,
                926,
                879,
                922,
                882,
                907,
                881,
                902,
                876,
                901,
                862,
                899,
                862,
                898,
                869,
                893,
                871,
                884,
                871,
                878,
                864,
                875,
                847,
                874,
                817,
                888,
                802,
                886,
                800,
                878,
                799,
                878,
                795,
                879,
                788,
                888,
                789,
                891,
                796
            ],
            "class": "vehicle"
        },
        {
            "polygon": [
                1073,
                792,
                1084,
                775,
                1097,
                761,
                1102,
                758,
                1115,
                758,
                1119,
                761,
                1148,
                760,
                1156,
                756,
                1162,
                757,
                1178,
                769,
                1185,
                778,
                1189,
                798,
                1192,
                809,
                1198,
                801,
                1210,
                797,
                1201,
                797,
                1201,
                789,
                1207,
                785,
                1214,
                784,
                1217,
                789,
                1232,
                772,
                1248,
                760,
                1257,
                756,
                1287,
                752,
                1335,
                752,
                1376,
                757,
                1404,
                782,
                1420,
                802,
                1420,
                830,
                1415,
                850,
                1411,
                875,
                1407,
                878,
                1390,
                879,
                1382,
                876,
                1378,
                863,
                1339,
                861,
                1321,
                863,
                1299,
                864,
                1296,
                873,
                1285,
                884,
                1274,
                886,
                1258,
                883,
                1254,
                875,
                1251,
                862,
                1221,
                859,
                1219,
                868,
                1212,
                872,
                1201,
                871,
                1192,
                866,
                1189,
                854,
                1189,
                849,
                1183,
                852,
                1171,
                852,
                1166,
                848,
                1163,
                837,
                1122,
                839,
                1119,
                849,
                1113,
                851,
                1101,
                850,
                1096,
                848,
                1094,
                838,
                1080,
                837,
                1079,
                844,
                1076,
                845,
                1070,
                844,
                1066,
                840,
                1066,
                825,
                1068,
                804,
                1071,
                797,
                1065,
                797,
                1066,
                792
            ],
            "class": "vehicle"
        },
        {
            "polygon": [
                1920,
                665,
                1815,
                671,
                1718,
                684,
                1637,
                703,
                1604,
                720,
                1569,
                750,
                1523,
                807,
                1507,
                808,
                1491,
                812,
                1478,
                818,
                1474,
                824,
                1472,
                833,
                1473,
                838,
                1476,
                848,
                1453,
                870,
                1440,
                896,
                1433,
                960,
                1435,
                998,
                1438,
                1057,
                1442,
                1069,
                1446,
                1080,
                1520,
                1080,
                1529,
                1069,
                1531,
                1056,
                1611,
                1080,
                1920,
                1080
            ],
            "class": "vehicle"
        },
        {
            "polygon": [
                886,
                611,
                869,
                639,
                869,
                643,
                904,
                643,
                904,
                639,
                889,
                610
            ],
            "class": "trafficSign"
        },
        {
            "polygon": [
                920,
                919,
                940,
                920,
                1070,
                1010,
                1170,
                1080,
                1129,
                1080,
                1015,
                993
            ],
            "class": "whiteLane"
        },
        {
            "polygon": [
                1082,
                858,
                1094,
                858,
                1195,
                878,
                1268,
                892,
                1309,
                899,
                1293,
                902,
                1177,
                878,
                1124,
                869
            ],
            "class": "whiteLane"
        }
    ]
}