{
    "in_vehicle": {
        "wheel_speed_mps": 8.0264548611,
        "yaw_rate_dps": 1.3300000000,
        "acceleration_x_mps2": -0.3700000000,
        "acceleration_y_mps2": 0.0900000000,
        "turn_signal": 0,
        "steering_angle_deg": 9.3000000000,
        "gear": 3
    },
    "scc_radar": {
        "object_count": 34,
        "objects_info": [
            {
                "id": 2,
                "status": 4,
                "lateral_rate_mps": 3.5000000000,
                "angle_deg": -5.6000000000,
                "range_m": 127.0000000000,
                "acceleration_mps2": 0.0000000000,
                "speed_mps": -8.1400000000,
                "width_m": 0.0000000000,
                "pos_x_m": 126.3938797977,
                "pos_y_m": 12.3930282694,
                "relative_speed_x_mps": -9.2682608429,
                "relative_speed_y_mps": 3.5000000000,
                "absolute_speed_x_mps": -9.5559387092,
                "absolute_speed_y_mps": 6.4793702360,
                "on_coming": false
            },
            {
                "id": 3,
                "status": 3,
                "lateral_rate_mps": -0.5000000000,
                "angle_deg": -3.9000000000,
                "range_m": 31.8000000000,
                "acceleration_mps2": 0.4500000000,
                "speed_mps": -2.6600000000,
                "width_m": 2.0000000000,
                "pos_x_m": 31.7263600670,
                "pos_y_m": 2.1628862432,
                "relative_speed_x_mps": -2.7913093392,
                "relative_speed_y_mps": -0.5000000000,
                "absolute_speed_x_mps": -2.8415161560,
                "absolute_speed_y_mps": 0.2818645504,
                "on_coming": false
            },
            {
                "id": 4,
                "status": 3,
                "lateral_rate_mps": -2.0000000000,
                "angle_deg": 7.1000000000,
                "range_m": 53.3000000000,
                "acceleration_mps2": 0.1000000000,
                "speed_mps": -8.1600000000,
                "width_m": 1.5000000000,
                "pos_x_m": 52.8912922893,
                "pos_y_m": -6.5879587103,
                "relative_speed_x_mps": -8.4607178576,
                "relative_speed_y_mps": -2.0000000000,
                "absolute_speed_x_mps": -8.3077923688,
                "absolute_speed_y_mps": -0.7268364378,
                "on_coming": false
            },
            {
                "id": 6,
                "status": 3,
                "lateral_rate_mps": -1.0000000000,
                "angle_deg": -16.9000000000,
                "range_m": 36.7000000000,
                "acceleration_mps2": 0.6500000000,
                "speed_mps": -7.2800000000,
                "width_m": 0.0000000000,
                "pos_x_m": 35.1150585349,
                "pos_y_m": 10.6687705051,
                "relative_speed_x_mps": -8.0378010438,
                "relative_speed_y_mps": -1.0000000000,
                "absolute_speed_x_mps": -8.2854539231,
                "absolute_speed_y_mps": -0.1394740019,
                "on_coming": false
            },
            {
                "id": 9,
                "status": 3,
                "lateral_rate_mps": -0.5000000000,
                "angle_deg": -7.2000000000,
                "range_m": 68.9000000000,
                "acceleration_mps2": 1.6000000000,
                "speed_mps": 2.2900000000,
                "width_m": 0.0000000000,
                "pos_x_m": 68.3567029206,
                "pos_y_m": 8.6354597926,
                "relative_speed_x_mps": 2.3537602634,
                "relative_speed_y_mps": -0.5000000000,
                "absolute_speed_x_mps": 2.1533063796,
                "absolute_speed_y_mps": 1.1321602687,
                "on_coming": false
            },
            {
                "id": 10,
                "status": 3,
                "lateral_rate_mps": -2.0000000000,
                "angle_deg": -25.9000000000,
                "range_m": 23.0000000000,
                "acceleration_mps2": 0.6500000000,
                "speed_mps": -6.5000000000,
                "width_m": 0.0000000000,
                "pos_x_m": 20.6898289160,
                "pos_y_m": 10.0464411325,
                "relative_speed_x_mps": -8.6711882273,
                "relative_speed_y_mps": -2.0000000000,
                "absolute_speed_x_mps": -8.9043950502,
                "absolute_speed_y_mps": -1.4743251124,
                "on_coming": false
            },
            {
                "id": 13,
                "status": 3,
                "lateral_rate_mps": -0.0000000000,
                "angle_deg": 0.0000000000,
                "range_m": 13.3000000000,
                "acceleration_mps2": 0.0500000000,
                "speed_mps": -1.8400000000,
                "width_m": 2.0000000000,
                "pos_x_m": 13.3000000000,
                "pos_y_m": -0.0000000000,
                "relative_speed_x_mps": -1.8400000000,
                "relative_speed_y_mps": -0.0000000000,
                "absolute_speed_x_mps": -1.8400000000,
                "absolute_speed_y_mps": 0.3541356828,
                "on_coming": false
            },
            {
                "id": 16,
                "status": 2,
                "lateral_rate_mps": -0.5000000000,
                "angle_deg": 5.4000000000,
                "range_m": 60.0000000000,
                "acceleration_mps2": 0.0000000000,
                "speed_mps": -8.1000000000,
                "width_m": 1.0000000000,
                "pos_x_m": 59.7337178762,
                "pos_y_m": -5.6464987991,
                "relative_speed_x_mps": -8.1196923630,
                "relative_speed_y_mps": -0.5000000000,
                "absolute_speed_x_mps": -7.9886208694,
                "absolute_speed_y_mps": 0.9319959598,
                "on_coming": false
            },
            {
                "id": 17,
                "status": 3,
                "lateral_rate_mps": -0.0000000000,
                "angle_deg": -6.0000000000,
                "range_m": 53.0000000000,
                "acceleration_mps2": 1.5500000000,
                "speed_mps": -0.8200000000,
                "width_m": 0.0000000000,
                "pos_x_m": 52.7096604545,
                "pos_y_m": 5.5400085532,
                "relative_speed_x_mps": -0.8245167892,
                "relative_speed_y_mps": -0.0000000000,
                "absolute_speed_x_mps": -0.9531163377,
                "absolute_speed_y_mps": 1.2689473644,
                "on_coming": false
            },
            {
                "id": 18,
                "status": 1,
                "lateral_rate_mps": -0.0000000000,
                "angle_deg": 8.1000000000,
                "range_m": 49.1000000000,
                "acceleration_mps2": 0.0000000000,
                "speed_mps": -43.7200000000,
                "width_m": 0.0000000000,
                "pos_x_m": 48.6101615939,
                "pos_y_m": -6.9182504881,
                "relative_speed_x_mps": -44.1605608707,
                "relative_speed_y_mps": -0.0000000000,
                "absolute_speed_x_mps": -43.9999683588,
                "absolute_speed_y_mps": 1.1737861932,
                "on_coming": false
            },
            {
                "id": 19,
                "status": 3,
                "lateral_rate_mps": -1.7500000000,
                "angle_deg": -4.7000000000,
                "range_m": 42.8000000000,
                "acceleration_mps2": 1.4000000000,
                "speed_mps": -2.2100000000,
                "width_m": 2.0000000000,
                "pos_x_m": 42.6560801558,
                "pos_y_m": 3.5069681694,
                "relative_speed_x_mps": -3.4206566371,
                "relative_speed_y_mps": -1.7500000000,
                "absolute_speed_x_mps": -3.5020634651,
                "absolute_speed_y_mps": -0.7144251791,
                "on_coming": false
            },
            {
                "id": 20,
                "status": 3,
                "lateral_rate_mps": 1.5000000000,
                "angle_deg": -8.9000000000,
                "range_m": 124.5000000000,
                "acceleration_mps2": -0.0500000000,
                "speed_mps": 4.4800000000,
                "width_m": 0.0000000000,
                "pos_x_m": 123.0010032883,
                "pos_y_m": 19.2614430943,
                "relative_speed_x_mps": 5.2199658380,
                "relative_speed_y_mps": 1.5000000000,
                "absolute_speed_x_mps": 4.7728522891,
                "absolute_speed_y_mps": 4.4006118040,
                "on_coming": false
            },
            {
                "id": 21,
                "status": 3,
                "lateral_rate_mps": -0.2500000000,
                "angle_deg": 15.9000000000,
                "range_m": 32.4000000000,
                "acceleration_mps2": 0.8000000000,
                "speed_mps": -7.7400000000,
                "width_m": 1.5000000000,
                "pos_x_m": 31.1604184294,
                "pos_y_m": -8.8762786856,
                "relative_speed_x_mps": -7.9845193135,
                "relative_speed_y_mps": -0.2500000000,
                "absolute_speed_x_mps": -7.7784753300,
                "absolute_speed_y_mps": 0.5187274156,
                "on_coming": false
            },
            {
                "id": 25,
                "status": 1,
                "lateral_rate_mps": -0.0000000000,
                "angle_deg": 5.1000000000,
                "range_m": 80.0000000000,
                "acceleration_mps2": 0.0000000000,
                "speed_mps": -8.0500000000,
                "width_m": 0.0000000000,
                "pos_x_m": 79.6832852329,
                "pos_y_m": -7.1115437493,
                "relative_speed_x_mps": -8.0819960939,
                "relative_speed_y_mps": -0.0000000000,
                "absolute_speed_x_mps": -7.9169166890,
                "absolute_speed_y_mps": 1.8950828540,
                "on_coming": false
            },
            {
                "id": 26,
                "status": 1,
                "lateral_rate_mps": -0.0000000000,
                "angle_deg": -9.4000000000,
                "range_m": 32.6000000000,
                "acceleration_mps2": 0.0000000000,
                "speed_mps": -2.3400000000,
                "width_m": 0.0000000000,
                "pos_x_m": 32.1622524684,
                "pos_y_m": 5.3244263691,
                "relative_speed_x_mps": -2.3718488024,
                "relative_speed_y_mps": -0.0000000000,
                "absolute_speed_x_mps": -2.4954440677,
                "absolute_speed_y_mps": 0.7919828680,
                "on_coming": false
            },
            {
                "id": 31,
                "status": 7,
                "lateral_rate_mps": 0.2500000000,
                "angle_deg": -22.9000000000,
                "range_m": 38.4000000000,
                "acceleration_mps2": 0.0000000000,
                "speed_mps": -7.6700000000,
                "width_m": 0.0000000000,
                "pos_x_m": 35.3735195737,
                "pos_y_m": 14.9423596854,
                "relative_speed_x_mps": -8.2282234892,
                "relative_speed_y_mps": 0.2500000000,
                "absolute_speed_x_mps": -8.5750786773,
                "absolute_speed_y_mps": 1.1165256229,
                "on_coming": false
            },
            {
                "id": 32,
                "status": 3,
                "lateral_rate_mps": -1.7500000000,
                "angle_deg": -34.9000000000,
                "range_m": 15.0000000000,
                "acceleration_mps2": -0.7000000000,
                "speed_mps": -6.4100000000,
                "width_m": 3.0000000000,
                "pos_x_m": 12.3022781381,
                "pos_y_m": 8.5821881017,
                "relative_speed_x_mps": -9.3692205277,
                "relative_speed_y_mps": -1.7500000000,
                "absolute_speed_x_mps": -9.5684378221,
                "absolute_speed_y_mps": -1.4190243141,
                "on_coming": false
            },
            {
                "id": 33,
                "status": 4,
                "lateral_rate_mps": -1.5000000000,
                "angle_deg": 4.6000000000,
                "range_m": 48.3000000000,
                "acceleration_mps2": 0.7500000000,
                "speed_mps": 4.3200000000,
                "width_m": 0.0000000000,
                "pos_x_m": 48.1444198294,
                "pos_y_m": -3.8736080451,
                "relative_speed_x_mps": 4.9339520657,
                "relative_speed_y_mps": -1.5000000000,
                "absolute_speed_x_mps": 5.0238696607,
                "absolute_speed_y_mps": -0.3370250141,
                "on_coming": false
            },
            {
                "id": 35,
                "status": 1,
                "lateral_rate_mps": -0.0000000000,
                "angle_deg": -9.5000000000,
                "range_m": 33.1000000000,
                "acceleration_mps2": 0.0000000000,
                "speed_mps": -2.4700000000,
                "width_m": 0.0000000000,
                "pos_x_m": 32.6460534109,
                "pos_y_m": 5.4630757540,
                "relative_speed_x_mps": -2.5043455934,
                "relative_speed_y_mps": -0.0000000000,
                "absolute_speed_x_mps": -2.6311593101,
                "absolute_speed_y_mps": 0.8032132808,
                "on_coming": false
            },
            {
                "id": 36,
                "status": 4,
                "lateral_rate_mps": -2.0000000000,
                "angle_deg": 26.8000000000,
                "range_m": 23.6000000000,
                "acceleration_mps2": 0.2000000000,
                "speed_mps": -7.3700000000,
                "width_m": 0.0000000000,
                "pos_x_m": 21.0650253155,
                "pos_y_m": -10.6407099603,
                "relative_speed_x_mps": -7.7790577647,
                "relative_speed_y_mps": -2.0000000000,
                "absolute_speed_x_mps": -7.5320562514,
                "absolute_speed_y_mps": -1.4656157237,
                "on_coming": false
            },
            {
                "id": 37,
                "status": 3,
                "lateral_rate_mps": -3.0000000000,
                "angle_deg": -11.1000000000,
                "range_m": 54.7000000000,
                "acceleration_mps2": 1.0500000000,
                "speed_mps": -4.8500000000,
                "width_m": 3.5000000000,
                "pos_x_m": 53.6767087204,
                "pos_y_m": 10.5309515690,
                "relative_speed_x_mps": -6.9708226773,
                "relative_speed_y_mps": -3.0000000000,
                "absolute_speed_x_mps": -7.2152763824,
                "absolute_speed_y_mps": -1.7086046612,
                "on_coming": false
            },
            {
                "id": 39,
                "status": 3,
                "lateral_rate_mps": -1.0000000000,
                "angle_deg": 22.0000000000,
                "range_m": 26.4000000000,
                "acceleration_mps2": 0.9000000000,
                "speed_mps": -7.4300000000,
                "width_m": 1.0000000000,
                "pos_x_m": 24.4776537606,
                "pos_y_m": -9.8896140662,
                "relative_speed_x_mps": -7.7397862417,
                "relative_speed_y_mps": -1.0000000000,
                "absolute_speed_x_mps": -7.5102198266,
                "absolute_speed_y_mps": -0.3863987924,
                "on_coming": false
            },
            {
                "id": 41,
                "status": 3,
                "lateral_rate_mps": 0.5000000000,
                "angle_deg": 0.0000000000,
                "range_m": 38.8000000000,
                "acceleration_mps2": 0.1000000000,
                "speed_mps": 4.6300000000,
                "width_m": 0.0000000000,
                "pos_x_m": 38.8000000000,
                "pos_y_m": -0.0000000000,
                "relative_speed_x_mps": 4.6836844471,
                "relative_speed_y_mps": 0.5000000000,
                "absolute_speed_x_mps": 4.6836844471,
                "absolute_speed_y_mps": 1.4460640986,
                "on_coming": false
            },
            {
                "id": 42,
                "status": 3,
                "lateral_rate_mps": -1.0000000000,
                "angle_deg": -20.8000000000,
                "range_m": 29.0000000000,
                "acceleration_mps2": 0.4500000000,
                "speed_mps": -6.6000000000,
                "width_m": 0.5000000000,
                "pos_x_m": 27.1099446155,
                "pos_y_m": 10.2981019098,
                "relative_speed_x_mps": -7.5732200916,
                "relative_speed_y_mps": -1.0000000000,
                "absolute_speed_x_mps": -7.8122686857,
                "absolute_speed_y_mps": -0.3252957431,
                "on_coming": false
            },
            {
                "id": 43,
                "status": 4,
                "lateral_rate_mps": -1.0000000000,
                "angle_deg": 30.8000000000,
                "range_m": 20.4000000000,
                "acceleration_mps2": 1.5000000000,
                "speed_mps": -6.7900000000,
                "width_m": 1.5000000000,
                "pos_x_m": 17.5227818974,
                "pos_y_m": -10.4456744434,
                "relative_speed_x_mps": -7.4443538986,
                "relative_speed_y_mps": -1.0000000000,
                "absolute_speed_x_mps": -7.2018797212,
                "absolute_speed_y_mps": -0.5478413917,
                "on_coming": false
            },
            {
                "id": 44,
                "status": 4,
                "lateral_rate_mps": 6.7500000000,
                "angle_deg": 5.7000000000,
                "range_m": 68.4000000000,
                "acceleration_mps2": 0.0000000000,
                "speed_mps": -8.1100000000,
                "width_m": 0.0000000000,
                "pos_x_m": 68.0618009853,
                "pos_y_m": -6.7934708825,
                "relative_speed_x_mps": -12.9995634263,
                "relative_speed_y_mps": 6.7500000000,
                "absolute_speed_x_mps": -12.8418674083,
                "absolute_speed_y_mps": 8.3753147457,
                "on_coming": false
            },
            {
                "id": 46,
                "status": 2,
                "lateral_rate_mps": -0.5000000000,
                "angle_deg": -8.2000000000,
                "range_m": 147.1000000000,
                "acceleration_mps2": 0.0000000000,
                "speed_mps": -8.0900000000,
                "width_m": 0.0000000000,
                "pos_x_m": 145.5960835665,
                "pos_y_m": 20.9807161481,
                "relative_speed_x_mps": -8.2758793431,
                "relative_speed_y_mps": -0.5000000000,
                "absolute_speed_x_mps": -8.7629021695,
                "absolute_speed_y_mps": 2.9251086696,
                "on_coming": false
            },
            {
                "id": 48,
                "status": 4,
                "lateral_rate_mps": 0.5000000000,
                "angle_deg": 36.1000000000,
                "range_m": 18.2000000000,
                "acceleration_mps2": 0.9000000000,
                "speed_mps": -6.6800000000,
                "width_m": 2.0000000000,
                "pos_x_m": 14.7054158869,
                "pos_y_m": -10.7233737038,
                "relative_speed_x_mps": -8.6609499672,
                "relative_speed_y_mps": 0.5000000000,
                "absolute_speed_x_mps": -8.4120295904,
                "absolute_speed_y_mps": 0.8867594318,
                "on_coming": false
            },
            {
                "id": 49,
                "status": 2,
                "lateral_rate_mps": 0.2500000000,
                "angle_deg": 13.9000000000,
                "range_m": 36.2000000000,
                "acceleration_mps2": 0.0000000000,
                "speed_mps": -7.8200000000,
                "width_m": 0.0000000000,
                "pos_x_m": 35.1399366331,
                "pos_y_m": -8.6962551377,
                "relative_speed_x_mps": -8.1254695023,
                "relative_speed_y_mps": 0.2500000000,
                "absolute_speed_x_mps": -7.9236043836,
                "absolute_speed_y_mps": 1.1111034904,
                "on_coming": false
            },
            {
                "id": 50,
                "status": 1,
                "lateral_rate_mps": -0.0000000000,
                "angle_deg": -11.2000000000,
                "range_m": 52.2000000000,
                "acceleration_mps2": 0.0000000000,
                "speed_mps": -62.8000000000,
                "width_m": 0.0000000000,
                "pos_x_m": 51.2058591092,
                "pos_y_m": 10.1390331337,
                "relative_speed_x_mps": -64.0192364121,
                "relative_speed_y_mps": -0.0000000000,
                "absolute_speed_x_mps": -64.2545925620,
                "absolute_speed_y_mps": 1.2340398057,
                "on_coming": false
            },
            {
                "id": 51,
                "status": 1,
                "lateral_rate_mps": -0.0000000000,
                "angle_deg": -28.7000000000,
                "range_m": 17.2000000000,
                "acceleration_mps2": 0.0000000000,
                "speed_mps": -6.6200000000,
                "width_m": 0.0000000000,
                "pos_x_m": 15.0869140157,
                "pos_y_m": 8.2598441560,
                "relative_speed_x_mps": -7.5472028197,
                "relative_speed_y_mps": -0.0000000000,
                "absolute_speed_x_mps": -7.7389375831,
                "absolute_speed_y_mps": 0.3956151017,
                "on_coming": false
            },
            {
                "id": 57,
                "status": 3,
                "lateral_rate_mps": -1.7500000000,
                "angle_deg": 8.9000000000,
                "range_m": 48.5000000000,
                "acceleration_mps2": 0.4500000000,
                "speed_mps": -8.1200000000,
                "width_m": 0.5000000000,
                "pos_x_m": 47.9160534898,
                "pos_y_m": -7.5034537355,
                "relative_speed_x_mps": -8.3214583459,
                "relative_speed_y_mps": -1.7500000000,
                "absolute_speed_x_mps": -8.1472815818,
                "absolute_speed_y_mps": -0.5923260543,
                "on_coming": false
            },
            {
                "id": 60,
                "status": 3,
                "lateral_rate_mps": -0.5000000000,
                "angle_deg": 12.5000000000,
                "range_m": 41.4000000000,
                "acceleration_mps2": 0.8000000000,
                "speed_mps": -7.8800000000,
                "width_m": 0.0000000000,
                "pos_x_m": 40.4186546948,
                "pos_y_m": -8.9606000170,
                "relative_speed_x_mps": -7.9918186960,
                "relative_speed_y_mps": -0.5000000000,
                "absolute_speed_x_mps": -7.7838173716,
                "absolute_speed_y_mps": 0.4836377343,
                "on_coming": false
            },
            {
                "id": 62,
                "status": 1,
                "lateral_rate_mps": -0.0000000000,
                "angle_deg": -18.2000000000,
                "range_m": 32.1000000000,
                "acceleration_mps2": 0.0000000000,
                "speed_mps": -7.0600000000,
                "width_m": 0.0000000000,
                "pos_x_m": 30.4941028539,
                "pos_y_m": 10.0259508842,
                "relative_speed_x_mps": -7.4317975867,
                "relative_speed_y_mps": -0.0000000000,
                "absolute_speed_x_mps": -7.6645287720,
                "absolute_speed_y_mps": 0.7532603128,
                "on_coming": false
            }
        ]
    },
    "backlight": {
        "max_intensity": 177
    },
    "sync": {
        "tick_frame": 167
    },
    "gps": {
        "latitude_deg": 37.5267716061,
        "longitude_deg": 126.9531363516,
        "heading_deg": 178.2800000000,
        "height_m": 42.6580000000
    }
}